signet/__init__.py
signet/train_classifier.py
signet/train_errorfinder.py
signet/train_finetuner.py
signet/train_generator.py
signet/train_nummutnet.py
signet/loggers/__init__.py
signet/loggers/classifier_logger.py
signet/loggers/errorfinder_logger.py
signet/loggers/finetuner_logger.py
signet/loggers/generator_logger.py
signet/loggers/nummut_logger.py
signet/models/__init__.py
signet/models/baseline.py
signet/models/classifier.py
signet/models/errorfinder.py
signet/models/finetuner.py
signet/models/generator.py
signet/models/nummut.py
signet/modules/__init__.py
signet/modules/classified_tunning_error.py
signet/modules/combined_finetuner.py
signet/modules/signet_module.py
signet/trainers/__init__.py
signet/trainers/classifier_trainer.py
signet/trainers/error_trainer.py
signet/trainers/finetuner_crossvalidation.py
signet/trainers/finetuner_trainer.py
signet/trainers/generator_trainer.py
signet/trainers/nummut_trainer.py
signaturenet-0.0.0.dist-info/LICENSE
signaturenet-0.0.0.dist-info/METADATA
signaturenet-0.0.0.dist-info/WHEEL
signaturenet-0.0.0.dist-info/top_level.txt
signaturenet-0.0.0.dist-info/RECORD
