Metadata-Version: 2.1
Name: signaturenet
Version: 0.0.0
Summary: Package to manipulate mutational processes.
Home-page: https://github.com/weghornlab/SigNet
License-File: LICENSE
Requires-Dist: torch (==1.11)
Requires-Dist: scipy
Requires-Dist: numpy (==1.23.3)
Requires-Dist: matplotlib (==3.3.4)
Requires-Dist: pandas
Requires-Dist: seaborn (==0.11.1)
Requires-Dist: scikit-optimize (==0.8.1)
Requires-Dist: tqdm (==4.59.0)
Requires-Dist: pyparsing (==2.4.7)
Requires-Dist: gaussian-process (==0.0.14)
Requires-Dist: PyYAML (==6.0)
Requires-Dist: scikit-learn
Requires-Dist: openpyxl
Requires-Dist: tensorboard
Requires-Dist: wandb
